pd_ai_agent_core/__init__.py
pd_ai_agent_core/common/__init__.py
pd_ai_agent_core/common/constants.py
pd_ai_agent_core/common/defaults.py
pd_ai_agent_core/common/message_status.py
pd_ai_agent_core/core_types/__init__.py
pd_ai_agent_core/core_types/background_agent.py
pd_ai_agent_core/core_types/content_message.py
pd_ai_agent_core/core_types/llm_chat_ai_agent.py
pd_ai_agent_core/core_types/session.py
pd_ai_agent_core/core_types/session_channel.py
pd_ai_agent_core/core_types/session_context.py
pd_ai_agent_core/core_types/session_service.py
pd_ai_agent_core/core_types/session_type.py
pd_ai_agent_core/events/__init__.py
pd_ai_agent_core/events/prlctl_event_item.py
pd_ai_agent_core/helpers/__init__.py
pd_ai_agent_core/helpers/image.py
pd_ai_agent_core/helpers/strings.py
pd_ai_agent_core/helpers/versions.py
pd_ai_agent_core/messages/__init__.py
pd_ai_agent_core/messages/background_message.py
pd_ai_agent_core/messages/chat_message.py
pd_ai_agent_core/messages/command_message.py
pd_ai_agent_core/messages/config_message.py
pd_ai_agent_core/messages/constants.py
pd_ai_agent_core/messages/error_message.py
pd_ai_agent_core/messages/event_message.py
pd_ai_agent_core/messages/log_message.py
pd_ai_agent_core/messages/message.py
pd_ai_agent_core/messages/notification_message.py
pd_ai_agent_core/messages/system_message.py
pd_ai_agent_core/parallels_desktop/__init__.py
pd_ai_agent_core/parallels_desktop/clone_vm.py
pd_ai_agent_core/parallels_desktop/constants.py
pd_ai_agent_core/parallels_desktop/datasource.py
pd_ai_agent_core/parallels_desktop/delete_vm.py
pd_ai_agent_core/parallels_desktop/execute_on_vm.py
pd_ai_agent_core/parallels_desktop/get_vm_image_text.py
pd_ai_agent_core/parallels_desktop/get_vm_os_version.py
pd_ai_agent_core/parallels_desktop/get_vm_screenshot.py
pd_ai_agent_core/parallels_desktop/get_vms.py
pd_ai_agent_core/parallels_desktop/get_vms_from_prlctl.py
pd_ai_agent_core/parallels_desktop/helpers.py
pd_ai_agent_core/parallels_desktop/os.py
pd_ai_agent_core-0.1.20.dist-info/licenses/LICENSE
pd_ai_agent_core-0.1.20.dist-info/METADATA
pd_ai_agent_core-0.1.20.dist-info/WHEEL
pd_ai_agent_core-0.1.20.dist-info/top_level.txt
pd_ai_agent_core-0.1.20.dist-info/RECORD
